whissle_mcp/__init__.py
whissle_mcp/__main__.py
whissle_mcp/server.py
whissle_mcp/utils.py
mseep_whissle_mcp-0.1.0.dist-info/METADATA
mseep_whissle_mcp-0.1.0.dist-info/WHEEL
mseep_whissle_mcp-0.1.0.dist-info/top_level.txt
mseep_whissle_mcp-0.1.0.dist-info/RECORD
