Metadata-Version: 2.4
Name: mseep-whissle-mcp
Version: 0.1.0
Summary: Whissle MCP Server
Home-page: https://github.com/mseep
Author: mseep
Author-email: support@skydeck.ai
Maintainer: mseep
Maintainer-email: support@skydeck.ai
Keywords: mseep,whissle,mcp,speech-to-text,translation,summarization
Classifier: Programming Language :: Python :: 3
Classifier: License :: OSI Approved :: MIT License
Classifier: Operating System :: OS Independent
Requires-Python: >=3.6
Requires-Dist: mcp[cli]>=1.6.0
Requires-Dist: fastapi==0.109.2
Requires-Dist: uvicorn==0.27.1
Requires-Dist: python-dotenv==1.0.1
Requires-Dist: pydantic>=2.6.1
Requires-Dist: httpx==0.28.1
Requires-Dist: whissle>=0.0.1
Dynamic: author
Dynamic: author-email
Dynamic: classifier
Dynamic: description
Dynamic: description-content-type
Dynamic: home-page
Dynamic: keywords
Dynamic: maintainer
Dynamic: maintainer-email
Dynamic: requires-dist
Dynamic: requires-python
Dynamic: summary
